Metadata-Version: 1.1
Name: redwing
Version: 0.0.1
Summary: Inspect a CSV file and determine data types to build a table to contain it.
Home-page: https://github.com/briandailey/redwing
Author: Brian Dailey
Author-email: brian@realm3.com
License: MIT
Keywords: data csv sql
Platform: UNKNOWN
Classifier: Development Status :: 3 - Alpha
Classifier: Intended Audience :: Developers
Classifier: Topic :: Software Development :: Build Tools
Classifier: License :: OSI Approved :: MIT License
Classifier: Programming Language :: Python :: 3.5
